fifo_folder/FIFOFolder.py
fifo_folder/FIFOManager.py
fifo_folder/__init__.py
fifo_folder/utils.py
fifo_folder-0.3.0.dist-info/METADATA
fifo_folder-0.3.0.dist-info/WHEEL
fifo_folder-0.3.0.dist-info/licenses/LICENSE
fifo_folder-0.3.0.dist-info/RECORD
