Metadata-Version: 2.4
Name: fifo-folder
Version: 0.3.0
Summary: A FIFO folder management library that manages files using queue-like principles.
Project-URL: Homepage, https://github.com/huang2002/fifo_folder
Project-URL: Changelog, https://github.com/huang2002/fifo_folder/blob/main/CHANGELOG.md
Project-URL: License, https://github.com/huang2002/fifo_folder/blob/main/LICENSE
Author-email: huang2002 <huanghaihua2002@qq.com>
License-Expression: ISC
License-File: LICENSE
Classifier: License :: OSI Approved :: ISC License (ISCL)
Classifier: Operating System :: OS Independent
Classifier: Programming Language :: Python :: 3
Requires-Python: >=3.12
